bungeegum/__init__.py
bungeegum/_version.py
bungeegum/bg.py
bungeegum/com.zetier.bungeegum-debug.apk
bungeegum/fork_exec.js
bungeegum/run_shellcode.js
bungeegum-0.1.0.dist-info/METADATA
bungeegum-0.1.0.dist-info/WHEEL
bungeegum-0.1.0.dist-info/entry_points.txt
bungeegum-0.1.0.dist-info/top_level.txt
bungeegum-0.1.0.dist-info/RECORD
