Metadata-Version: 2.1
Name: bungeegum
Version: 0.1.0
Summary: A set of tools to test payloads within the context of a standard Android application
Author: Zetier
Project-URL: Repository, https://github.com/Zetier/bungeegum
Project-URL: Issues, https://github.com/Zetier/bungeegum/issues
Keywords: bungeegum,automation,android,testing,openstf,rce
Classifier: Intended Audience :: Developers
Classifier: License :: OSI Approved :: GNU General Public License v2 (GPLv2)
Classifier: Natural Language :: English
Classifier: Programming Language :: Python :: 3.8
Requires-Python: >=3.8
Requires-Dist: adbutils ==2.7.*
Requires-Dist: frida ==16.4.10
Requires-Dist: importlib-resources ==6.4.*
